serde_ext/__init__.py
serde_ext/fields.py
serde_ext/validate.py
serde_ext-0.1.0.dist-info/LICENSE
serde_ext-0.1.0.dist-info/METADATA
serde_ext-0.1.0.dist-info/WHEEL
serde_ext-0.1.0.dist-info/top_level.txt
serde_ext-0.1.0.dist-info/RECORD
